gittraffic/__init__.py
gittraffic/__main__.py
gittraffic/gitplot.py
gittraffic/gittraffic.py
gittraffic-0.0.6.dist-info/DESCRIPTION.rst
gittraffic-0.0.6.dist-info/METADATA
gittraffic-0.0.6.dist-info/RECORD
gittraffic-0.0.6.dist-info/WHEEL
gittraffic-0.0.6.dist-info/entry_points.txt
gittraffic-0.0.6.dist-info/metadata.json
gittraffic-0.0.6.dist-info/top_level.txt
