Metadata-Version: 2.0
Name: gittraffic
Version: 0.0.6
Summary: Follow your git traffic per package in a github repo
Home-page: https://github.com/kootenpv/gittraffic
Author: Pascal van Kooten
Author-email: kootenpv@gmail.com
License: GPL
Platform: any
Classifier: Environment :: Console
Classifier: Intended Audience :: Developers
Classifier: Intended Audience :: Customer Service
Classifier: License :: OSI Approved :: GNU General Public License v3 (GPLv3)
Classifier: Operating System :: Microsoft
Classifier: Operating System :: MacOS :: MacOS X
Classifier: Operating System :: Unix
Classifier: Operating System :: POSIX
Classifier: Programming Language :: Python
Classifier: Programming Language :: Python :: 2.7
Classifier: Programming Language :: Python :: 3
Classifier: Programming Language :: Python :: 3.3
Classifier: Programming Language :: Python :: 3.4
Classifier: Programming Language :: Python :: 3.5
Classifier: Topic :: Software Development
Classifier: Topic :: Software Development :: Build Tools
Classifier: Topic :: Software Development :: Debuggers
Classifier: Topic :: Software Development :: Libraries
Classifier: Topic :: Software Development :: Libraries :: Python Modules
Classifier: Topic :: System :: Software Distribution
Classifier: Topic :: Utilities
Requires-Dist: datetime
Requires-Dist: lxml
Requires-Dist: selenium
